baseadmin/__init__.py
baseadmin/config.py
baseadmin/endpoint.py
baseadmin/queue.py
baseadmin/storage.py
baseadmin/tools.py
baseadmin/backend/__init__.py
baseadmin/backend/cloud.py
baseadmin/backend/interface.py
baseadmin/backend/security.py
baseadmin/backend/socketio.py
baseadmin/backend/web.py
baseadmin/backend/api/__init__.py
baseadmin/backend/api/io/__init__.py
baseadmin/backend/api/io/clients.py
baseadmin/backend/api/rest/__init__.py
baseadmin/backend/api/rest/provisioning.py
baseadmin/backend/api/rest/registration.py
baseadmin/backend/api/rest/session.py
baseadmin/backend/repositories/__init__.py
baseadmin/backend/repositories/client.py
baseadmin/backend/repositories/group.py
baseadmin/backend/repositories/registration.py
baseadmin/backend/repositories/tokens.py
baseadmin/backend/repositories/users.py
baseadmin/backend/static/js/api.js
baseadmin/backend/static/js/client.js
baseadmin/backend/static/js/common.js
baseadmin/backend/static/js/dashboard.js
baseadmin/backend/static/js/group.js
baseadmin/backend/static/js/landing.js
baseadmin/backend/static/js/log.js
baseadmin/backend/static/js/master.js
baseadmin/backend/static/js/router.js
baseadmin/backend/static/js/socketio.js
baseadmin/backend/static/js/user.js
baseadmin/backend/static/vendor/js/Chart.min.js
baseadmin/backend/static/vendor/js/bootstrap-datetimepicker.min.js
baseadmin/backend/static/vendor/js/bootstrap.min.js
baseadmin/backend/static/vendor/js/html5shiv.min.js
baseadmin/backend/static/vendor/js/index.js.map
baseadmin/backend/static/vendor/js/jquery.min.js
baseadmin/backend/static/vendor/js/moment.min.js
baseadmin/backend/static/vendor/js/respond.min.js
baseadmin/backend/static/vendor/js/socket.io.slim.js
baseadmin/backend/static/vendor/js/socket.io.slim.js.map
baseadmin/backend/static/vendor/js/vue-chartjs.min.js
baseadmin/backend/static/vendor/js/vue-chartjs.min.js.map
baseadmin/backend/static/vendor/js/vue-form-generator.min.js
baseadmin/backend/static/vendor/js/vue-multiselect.min.js
baseadmin-1.0.13.dist-info/LICENSE.txt
baseadmin-1.0.13.dist-info/METADATA
baseadmin-1.0.13.dist-info/WHEEL
baseadmin-1.0.13.dist-info/top_level.txt
baseadmin-1.0.13.dist-info/RECORD
