Metadata-Version: 2.1
Name: baseadmin
Version: 1.0.13
Summary: A Pythonic base for building administrator tools for distributed (IoT) applications.
Home-page: https://github.com/christophevg/baseadmin
Author: Christophe VG
License: MIT
Platform: UNKNOWN
Classifier: Environment :: Console
Classifier: Development Status :: 4 - Beta
Classifier: Intended Audience :: Developers
Classifier: Intended Audience :: System Administrators
Classifier: Topic :: Software Development
Classifier: License :: OSI Approved :: MIT License
Classifier: Programming Language :: Python
Classifier: Programming Language :: Python :: 3.5
Classifier: Programming Language :: Python :: 3.6
Classifier: Programming Language :: Python :: 3.7
